{"csv-import-release-rollout":{"slug":"csv-import-release-rollout","branch":{"slug":"enable-csv-import","ratio":1,"feature":{"value":{},"enabled":false,"featureId":"this-is-included-for-desktop-pre-95-support"},"features":[{"value":{"csvImport":true},"enabled":true,"featureId":"cm-csv-import"}]},"active":true,"enrollmentId":"305dd049-5d02-453f-81ac-1c5211616571","experimentType":"rollout","source":"rs-loader","userFacingName":"CSV Import (Release Rollout)","userFacingDescription":"This rollout enables users to import logins from a CSV file from the about:logins page.","lastSeen":"2023-09-04T18:12:31.298Z","featureIds":["cm-csv-import"],"prefs":[{"name":"signon.management.page.fileImport.enabled","branch":"default","featureId":"cm-csv-import","variable":"csvImport","originalValue":false}],"isRollout":true},"pocket-newtab-existing-markets-tier-2-rollout":{"slug":"pocket-newtab-existing-markets-tier-2-rollout","branch":{"slug":"rollout","ratio":1,"feature":{"value":{},"enabled":false,"featureId":"this-is-included-for-desktop-pre-95-support"},"features":[{"value":{"regionBffConfig":"FR,IT,ES,IE,IN,CH,AT,BE"},"enabled":true,"featureId":"pocketNewtab"}]},"active":true,"enrollmentId":"a665ff80-e7da-4cc3-b140-c45f4dde4240","experimentType":"rollout","source":"rs-loader","userFacingName":"Pocket Newtab Existing Markets Tier 2 Rollout","userFacingDescription":"Pocket newtab API migration rollout.","lastSeen":"2023-09-04T18:12:31.439Z","featureIds":["pocketNewtab"],"prefs":[],"isRollout":true},"serp-ad-telemetry-rollout":{"slug":"serp-ad-telemetry-rollout","branch":{"slug":"control","ratio":1,"feature":{"value":{},"enabled":false,"featureId":"this-is-included-for-desktop-pre-95-support"},"features":[{"value":{"serpEventTelemetryEnabled":true},"enabled":true,"featureId":"search"}]},"active":true,"enrollmentId":"f4b11ac2-e341-4495-a8a7-a315b0437e7b","experimentType":"rollout","source":"rs-loader","userFacingName":"SERP Ad Telemetry Rollout","userFacingDescription":"Telemetry improvements.","lastSeen":"2023-09-04T18:12:31.531Z","featureIds":["search"],"prefs":[{"name":"browser.search.serpEventTelemetry.enabled","branch":"default","featureId":"search","variable":"serpEventTelemetryEnabled","originalValue":false}],"isRollout":true},"upgrade-spotlight-rollout":{"slug":"upgrade-spotlight-rollout","branch":{"slug":"treatment","ratio":1,"feature":{"value":{},"enabled":false,"featureId":"this-is-included-for-desktop-pre-95-support"},"features":[{"value":{"enabled":false},"enabled":true,"featureId":"upgradeDialog"}]},"active":true,"enrollmentId":"6f3a155a-167a-4187-ad60-ae4c7481e979","experimentType":"rollout","source":"rs-loader","userFacingName":"Upgrade Spotlight Rollout","userFacingDescription":"Experimenting on onboarding content when you upgrade Firefox.","lastSeen":"2023-09-05T20:04:42.258Z","featureIds":["upgradeDialog"],"prefs":[],"isRollout":true}}